khmer2number/__init__.py
khmer2number-0.0.1.dist-info/LICENSE
khmer2number-0.0.1.dist-info/METADATA
khmer2number-0.0.1.dist-info/WHEEL
khmer2number-0.0.1.dist-info/top_level.txt
khmer2number-0.0.1.dist-info/RECORD
